{"file:///home/vincent/typ2tex/convert.py":{"language":"Python","code":107,"comment":0,"blank":29},"file:///home/vincent/typ2tex/chat.py":{"language":"Python","code":23,"comment":0,"blank":8},"file:///home/vincent/typ2tex/test/test_main.py":{"language":"Python","code":40,"comment":0,"blank":7},"file:///home/vincent/typ2tex/test/test_chat.py":{"language":"Python","code":25,"comment":0,"blank":5},"file:///home/vincent/typ2tex/main.py":{"language":"Python","code":1075,"comment":0,"blank":88},"file:///home/vincent/typ2tex/.pandoc/temp.typ":{"language":"Typst","code":1,"comment":0,"blank":1},"file:///home/vincent/typ2tex/test/test_convert.py":{"language":"Python","code":15,"comment":0,"blank":3}}